gigaloader/__init__.py
gigaloader/gigaloader.py
gigaloader-1.0.0.dist-info/LICENSE
gigaloader-1.0.0.dist-info/METADATA
gigaloader-1.0.0.dist-info/WHEEL
gigaloader-1.0.0.dist-info/top_level.txt
gigaloader-1.0.0.dist-info/RECORD
